visitingcard/VisitingCard.py
visitingcard/__init__.py
visitingcard-0.0.19.dist-info/LICENCE.txt
visitingcard-0.0.19.dist-info/METADATA
visitingcard-0.0.19.dist-info/WHEEL
visitingcard-0.0.19.dist-info/top_level.txt
visitingcard-0.0.19.dist-info/RECORD
